django_bureaucracy/__init__.py
django_bureaucracy/admin.py
django_bureaucracy/engine.py
django_bureaucracy/models.py
django_bureaucracy/shortcuts.py
django_bureaucracy/templatetags.py
django_bureaucracy/migrations/0001_initial.py
django_bureaucracy/migrations/__init__.py
django_bureaucracy/tests/__init__.py
django_bureaucracy/tests/tests.py
django_bureaucracy-0.4.2.dist-info/DESCRIPTION.rst
django_bureaucracy-0.4.2.dist-info/METADATA
django_bureaucracy-0.4.2.dist-info/RECORD
django_bureaucracy-0.4.2.dist-info/WHEEL
django_bureaucracy-0.4.2.dist-info/metadata.json
django_bureaucracy-0.4.2.dist-info/top_level.txt
