Metadata-Version: 2.0
Name: django-bureaucracy
Version: 0.4.2
Summary: Django layer on top of the bureaucracy package
Home-page: UNKNOWN
Author: Maykin Media, Robin Ramael, Sergei Maertens
Author-email: robin.ramael@maykinmedia.nl,sergei@maykinmedia.nl
License: UNKNOWN
Platform: UNKNOWN
Classifier: Environment :: Web Environment
Classifier: Framework :: Django
Classifier: Framework :: Django :: 1.9
Classifier: Framework :: Django :: 1.10
Classifier: Intended Audience :: Developers
Classifier: Operating System :: OS Independent
Classifier: Programming Language :: Python
Classifier: Programming Language :: Python :: 3
Classifier: Programming Language :: Python :: 3.4
Classifier: Programming Language :: Python :: 3.5
Classifier: Topic :: Internet :: WWW/HTTP
Classifier: Topic :: Internet :: WWW/HTTP :: Dynamic Content
Requires-Dist: django
Requires-Dist: burocracy (>=0.4.1)
